tests/__init__.py
tests/test_llm_master.py
llm_master-0.1.0.dist-info/LICENSE
llm_master-0.1.0.dist-info/METADATA
llm_master-0.1.0.dist-info/WHEEL
llm_master-0.1.0.dist-info/top_level.txt
llm_master-0.1.0.dist-info/RECORD
