Metadata-Version: 2.1
Name: llm_master
Version: 0.1.0
Summary: A unified interface for interacting with multiple LLMs.
Home-page: https://github.com/Habatakurikei/llm_master
Author: Daisuke Yamaguchi
Author-email: daicom0204@gmail.com
Classifier: Development Status :: 3 - Alpha
Classifier: Intended Audience :: Developers
Classifier: License :: OSI Approved :: MIT License
Classifier: Operating System :: OS Independent
Classifier: Programming Language :: Python :: 3
Classifier: Programming Language :: Python :: 3.9
Classifier: Programming Language :: Python :: 3.10
Classifier: Programming Language :: Python :: 3.11
Classifier: Programming Language :: Python :: 3.12
Requires-Python: >=3.9
License-File: LICENSE
Requires-Dist: anthropic >=0.25.9
Requires-Dist: google-generativeai >=0.7.2
Requires-Dist: groq >=0.5.0
Requires-Dist: openai >=1.30.1
Provides-Extra: dev
Requires-Dist: pytest >=6.0 ; extra == 'dev'
Requires-Dist: flake8 >=6.0 ; extra == 'dev'
